{
  "recorded_at": "2026-07-18T12:28:30.651Z",
  "generated_at": "2026-07-18",
  "next_review": "2026-07-25 20:00 Asia/Taipei",
  "trend_count": 77,
  "recommendation_count": 6,
  "source_count": 42,
  "category_count": 25,
  "category_counts": {
    "AI投資ROI": 16,
    "AI成本治理": 8,
    "AI基礎建設與資料中心": 15,
    "資本市場與金融風險": 17,
    "Agentic AI與流程自動化": 8,
    "資料治理與AI-ready": 10,
    "AI規模化落地": 10,
    "高階幕僚與決策智能": 10,
    "AI信任與透明度": 17,
    "董事會AI治理": 13,
    "資安與數位韌性": 11,
    "EU AI監管與合規": 12,
    "地緣政治與能源風險": 20,
    "全球低成長與通膨": 14,
    "關稅貿易與區域布局": 13,
    "印度與新興市場": 6,
    "供應鏈韌性": 13,
    "AI供應鏈與半導體": 13,
    "歐洲AI產業政策": 12,
    "新創與生態系合作": 8,
    "未來工作與人機協作": 10,
    "人才重配置與再學習": 10,
    "CEO經營節奏與風險雷達": 22,
    "領導力接班與心理安全": 9,
    "高階學習產品與內容設計": 12
  },
  "parent_category_counts": {
    "科技與AI轉型": 18,
    "治理與社會信任": 16,
    "組織與人才": 12,
    "CEO經營環境": 13,
    "地緣政治與供應鏈": 12,
    "產業與商業模式": 6
  },
  "confidence_counts": {
    "B": 23,
    "A": 51,
    "C": 3
  },
  "source_type_counts": {
    "國際財經媒體": 3,
    "官方/金融機構": 5,
    "顧問/研究": 7,
    "CEO調查": 7,
    "官方/經濟機構": 3,
    "產業活動/媒體": 2,
    "國際組織/論壇": 1,
    "政策/研究": 1,
    "投資/研究": 1,
    "領導力研究": 1,
    "影音媒體": 1,
    "國際財經活動": 1,
    "國際影音媒體": 1,
    "國際財經媒體與產品訊號": 1,
    "歐洲官方/監管": 2,
    "歐洲官方/產業政策": 1,
    "歐洲國際財經媒體": 1,
    "歐洲科技媒體": 1,
    "AI研究": 2,
    "官方經濟機構": 4,
    "歐洲AI治理": 1,
    "CEO/董事會研究": 6,
    "組織/人才研究": 2,
    "影音/弱訊號": 1,
    "投資研究/國際財經媒體": 1,
    "國際財經媒體/能源訊號": 1,
    "企業領袖訪談/組織研究": 1,
    "產業研究/活動訊號": 1,
    "投資研究": 1,
    "國際財經媒體與影音": 1,
    "歐洲官方/國際財經媒體": 1,
    "顧問/領導力研究": 1,
    "貿易/供應鏈研究": 1,
    "能源研究": 1,
    "國際組織/風險研究": 1,
    "能源/產業研究": 1,
    "政府/監管機構": 2,
    "政府/財經媒體": 1,
    "顧問/AI研究": 2,
    "影音弱訊號": 1,
    "國際財經媒體/AI治理": 1,
    "官方/金融研究": 1,
    "國際財經媒體/能源治理": 1
  },
  "top_hot_trends": [
    {
      "id": "imf-war-technology-crosscurrents-202607",
      "title": "戰爭與科技交錯成為 CEO 下半年基準情境",
      "category": "CEO經營環境",
      "heat": 98,
      "confidence": "A"
    },
    {
      "id": "ai-cost-discipline",
      "title": "AI 成本紀律成為 CEO/CFO 議題",
      "category": "科技與AI轉型",
      "heat": 97,
      "confidence": "B"
    },
    {
      "id": "ai-capex-financial-link",
      "title": "AI 資本支出與金融穩定開始連動",
      "category": "科技與AI轉型",
      "heat": 97,
      "confidence": "A"
    },
    {
      "id": "ai-physical-economy-buildout",
      "title": "AI 下一波競爭移向實體經濟與基礎建設",
      "category": "科技與AI轉型",
      "heat": 97,
      "confidence": "A"
    },
    {
      "id": "bis-policy-discipline-ai-fragility-202606",
      "title": "AI 投資熱潮與金融脆弱性進入同一張風險圖",
      "category": "CEO經營環境",
      "heat": 97,
      "confidence": "A"
    },
    {
      "id": "data-center-power-demand-doubles",
      "title": "資料中心用電需求快速上升，電力成為 AI 規模化瓶頸",
      "category": "科技與AI轉型",
      "heat": 96,
      "confidence": "A"
    },
    {
      "id": "ceo-confidence-risk-stack-q2",
      "title": "CEO 信心轉弱，風險從單點事件變成整組經營壓力",
      "category": "CEO經營環境",
      "heat": 96,
      "confidence": "A"
    },
    {
      "id": "worldbank-growth-energy-risk-202606",
      "title": "能源衝擊與貿易不確定性壓低全球成長",
      "category": "地緣政治與供應鏈",
      "heat": 96,
      "confidence": "A"
    },
    {
      "id": "conference-board-ceo-risk-q2-2026",
      "title": "CEO 風險焦點從單點事件升級為跨部門風險治理",
      "category": "CEO經營環境",
      "heat": 95,
      "confidence": "A"
    },
    {
      "id": "middle-east-energy-risk",
      "title": "中東衝突與能源價格重新改寫策略假設",
      "category": "地緣政治與供應鏈",
      "heat": 94,
      "confidence": "A"
    }
  ],
  "recommended_courses": [
    {
      "id": "course-ceo-risk-radar",
      "title": "CEO 全局風險雷達：資安、地緣、能源與金融規範的季度節奏",
      "priority": 1,
      "category": "CEO經營環境",
      "heat": 96
    },
    {
      "id": "course-ai-capital-roi",
      "title": "AI 投資與資本紀律：從 capex 熱潮到董事會停損門檻",
      "priority": 2,
      "category": "科技與AI轉型",
      "heat": 95
    },
    {
      "id": "course-geopolitics-energy",
      "title": "能源、資料中心與供應鏈韌性：AI 成長背後的營運底盤",
      "priority": 3,
      "category": "地緣政治與供應鏈",
      "heat": 93
    },
    {
      "id": "course-trust-governance",
      "title": "董事會信任治理：AI 透明、frontier model 與內容責任",
      "priority": 4,
      "category": "治理與社會信任",
      "heat": 91
    },
    {
      "id": "course-human-ai-work",
      "title": "組織適應力與人機協作：從工具訓練到工作系統重設",
      "priority": 5,
      "category": "組織與人才",
      "heat": 90
    },
    {
      "id": "course-supply-chain-resilience",
      "title": "歐洲市場准入與可信供應鏈：合規、能源與科技主權",
      "priority": 6,
      "category": "地緣政治與供應鏈",
      "heat": 89
    }
  ]
}
